[{"Name":"fsadas","EloList":[{"ValidAfter":0,"Amount":1000.0,"Previous":null,"ValuePrevious":1000.0},{"ValidAfter":0,"Amount":1025.0,"Previous":{"ValidAfter":0,"Amount":1000.0,"Previous":null,"ValuePrevious":1000.0},"ValuePrevious":1000.0},{"ValidAfter":1,"Amount":1046.426844129581,"Previous":{"ValidAfter":0,"Amount":1025.0,"Previous":{"ValidAfter":0,"Amount":1000.0,"Previous":null,"ValuePrevious":1000.0},"ValuePrevious":1000.0},"ValuePrevious":1025.0},{"ValidAfter":0,"Amount":1064.9001390446631,"Previous":{"ValidAfter":1,"Amount":1046.426844129581,"Previous":{"ValidAfter":0,"Amount":1025.0,"Previous":{"ValidAfter":0,"Amount":1000.0,"Previous":null,"ValuePrevious":1000.0},"ValuePrevious":1000.0},"ValuePrevious":1025.0},"ValuePrevious":1046.426844129581},{"ValidAfter":3,"Amount":1105.667396376904,"Previous":{"ValidAfter":0,"Amount":1064.9001390446631,"Previous":{"ValidAfter":1,"Amount":1046.426844129581,"Previous":{"ValidAfter":0,"Amount":1025.0,"Previous":{"ValidAfter":0,"Amount":1000.0,"Previous":null,"ValuePrevious":1000.0},"ValuePrevious":1000.0},"ValuePrevious":1025.0},"ValuePrevious":1046.426844129581},"ValuePrevious":1064.9001390446631}]},{"Name":"dasdas","EloList":[{"ValidAfter":0,"Amount":1000.0,"Previous":null,"ValuePrevious":1000.0},{"ValidAfter":0,"Amount":975.0,"Previous":{"ValidAfter":0,"Amount":1000.0,"Previous":null,"ValuePrevious":1000.0},"ValuePrevious":1000.0},{"ValidAfter":1,"Amount":953.5731558704191,"Previous":{"ValidAfter":0,"Amount":975.0,"Previous":{"ValidAfter":0,"Amount":1000.0,"Previous":null,"ValuePrevious":1000.0},"ValuePrevious":1000.0},"ValuePrevious":975.0},{"ValidAfter":0,"Amount":935.09986095533691,"Previous":{"ValidAfter":1,"Amount":953.5731558704191,"Previous":{"ValidAfter":0,"Amount":975.0,"Previous":{"ValidAfter":0,"Amount":1000.0,"Previous":null,"ValuePrevious":1000.0},"ValuePrevious":1000.0},"ValuePrevious":975.0},"ValuePrevious":953.5731558704191},{"ValidAfter":4,"Amount":965.036276548378,"Previous":{"ValidAfter":0,"Amount":935.09986095533691,"Previous":{"ValidAfter":1,"Amount":953.5731558704191,"Previous":{"ValidAfter":0,"Amount":975.0,"Previous":{"ValidAfter":0,"Amount":1000.0,"Previous":null,"ValuePrevious":1000.0},"ValuePrevious":1000.0},"ValuePrevious":975.0},"ValuePrevious":953.5731558704191},"ValuePrevious":935.09986095533691}]},{"Name":"ggasga","EloList":[{"ValidAfter":0,"Amount":1000.0,"Previous":null,"ValuePrevious":1000.0},{"ValidAfter":3,"Amount":1004.6163713338796,"Previous":{"ValidAfter":0,"Amount":1000.0,"Previous":null,"ValuePrevious":1000.0},"ValuePrevious":1000.0},{"ValidAfter":4,"Amount":974.67995574083841,"Previous":{"ValidAfter":3,"Amount":1004.6163713338796,"Previous":{"ValidAfter":0,"Amount":1000.0,"Previous":null,"ValuePrevious":1000.0},"ValuePrevious":1000.0},"ValuePrevious":1004.6163713338796}]},{"Name":"gahaahha","EloList":[{"ValidAfter":0,"Amount":1000.0,"Previous":null,"ValuePrevious":1000.0}]},{"Name":"dsadasfga","EloList":[{"ValidAfter":0,"Amount":1000.0,"Previous":null,"ValuePrevious":1000.0},{"ValidAfter":3,"Amount":954.61637133387956,"Previous":{"ValidAfter":0,"Amount":1000.0,"Previous":null,"ValuePrevious":1000.0},"ValuePrevious":1000.0}]},{"Name":"gsagsadas","EloList":[{"ValidAfter":0,"Amount":1000.0,"Previous":null,"ValuePrevious":1000.0},{"ValidAfter":5,"Amount":1025.0,"Previous":{"ValidAfter":0,"Amount":1000.0,"Previous":null,"ValuePrevious":1000.0},"ValuePrevious":1000.0},{"ValidAfter":6,"Amount":1046.426844129581,"Previous":{"ValidAfter":5,"Amount":1025.0,"Previous":{"ValidAfter":0,"Amount":1000.0,"Previous":null,"ValuePrevious":1000.0},"ValuePrevious":1000.0},"ValuePrevious":1025.0}]},{"Name":"gdsgdgsgsd","EloList":[{"ValidAfter":0,"Amount":1000.0,"Previous":null,"ValuePrevious":1000.0},{"ValidAfter":5,"Amount":975.0,"Previous":{"ValidAfter":0,"Amount":1000.0,"Previous":null,"ValuePrevious":1000.0},"ValuePrevious":1000.0},{"ValidAfter":6,"Amount":953.5731558704191,"Previous":{"ValidAfter":5,"Amount":975.0,"Previous":{"ValidAfter":0,"Amount":1000.0,"Previous":null,"ValuePrevious":1000.0},"ValuePrevious":1000.0},"ValuePrevious":975.0}]}]